sgfixedincome_pkg/__init__.py
sgfixedincome_pkg/analysis.py
sgfixedincome_pkg/consolidate.py
sgfixedincome_pkg/equations.py
sgfixedincome_pkg/mas_api_client.py
sgfixedincome_pkg/scraper.py
sgfixedincome_pkg/streamlit_app/.streamlit/secrets.toml
sgfixedincome_pkg/streamlit_app/app.py
sgfixedincome_pkg-0.2.0.dist-info/entry_points.txt
sgfixedincome_pkg-0.2.0.dist-info/LICENSE
sgfixedincome_pkg-0.2.0.dist-info/METADATA
sgfixedincome_pkg-0.2.0.dist-info/WHEEL
sgfixedincome_pkg-0.2.0.dist-info/RECORD
