Metadata-Version: 2.1
Name: sgfixedincome_pkg
Version: 0.2.0
Summary: A package to aggregate fixed income products available to Singapore residents to earn yield on singapore dollars
Home-page: https://github.com/GidTay/sgfixedincome_pkg
License: MIT
Author: Gideon Tay
Requires-Python: >=3.12,<4.0
Classifier: License :: OSI Approved :: MIT License
Classifier: Programming Language :: Python :: 3
Classifier: Programming Language :: Python :: 3.12
Requires-Dist: beautifulsoup4 (>=4.12.3,<5.0.0)
Requires-Dist: matplotlib (>=3.9.3,<4.0.0)
Requires-Dist: numpy (>=2.2.0,<3.0.0)
Requires-Dist: pandas (>=2.2.3,<3.0.0)
Requires-Dist: pytz (>=2024.2,<2025.0)
Requires-Dist: requests (>=2.32.3,<3.0.0)
Requires-Dist: seaborn (>=0.13.2,<0.14.0)
Requires-Dist: streamlit (>=1.41.0,<2.0.0)
Requires-Dist: tzdata (>=2024.2,<2025.0)
Project-URL: Documentation, https://sgfixedincome-pkg.readthedocs.io/en/latest/
Project-URL: Repository, https://github.com/GidTay/sgfixedincome_pkg
